<?xml version="1.0" ?>
<interface uri="http://0install.de/feeds/Golly.xml" xmlns="http://zero-install.sourceforge.net/2004/injector/interface" xmlns:xsi="http://www.w3.org/2001/XMLSchema-instance" xsi:schemaLocation="http://zero-install.sourceforge.net/2004/injector/interface http://0install.de/schema/injector/interface/interface.xsd http://0install.de/schema/desktop-integration/capabilities http://0install.de/schema/desktop-integration/capabilities/capabilities.xsd">
  <name>Golly</name>
  <summary xml:lang="en">Game of Life simulator</summary>
  <summary xml:lang="de">Spiel des Lebens Simulator</summary>
  <description xml:lang="en">A cross-platform application for exploring Conway's Game of Life and other cellular automata. Features include an unbounded universe, fast generating algorithms, multiple layers, Perl/Python scripting, and a state-of-the-art pattern collection.</description>
  <description xml:lang="de">Eine Plattform-übergreifende Anwendung um Conway's Game of Life (Spiel des Lebens) und andere zelluläre Automaten zu erforschen. Zu den Features gehören ein Universum mit unbeschränkter Größe, schnelle erzeugende Algorithmen, mehrere Ebenden, Perl/Python Scripting und eine hochmoderne Sammlung von Mustern.</description>
  <homepage>http://golly.sourceforge.net/</homepage>
  <icon href="https://raw.githubusercontent.com/0install/0install.de-feeds/master/Golly.png" type="image/png"/>
  <icon href="https://raw.githubusercontent.com/0install/0install.de-feeds/master/Golly.ico" type="image/vnd.microsoft.icon"/>
  <category>Education</category>
  <group license="GPL v2 (GNU General Public License)">
    <implementation arch="Windows-*" id="sha1new=243025a430a3dfc14e7dd8c6f1db35db8a37561b" main="Golly.exe" released="2013-06-15" stability="stable" version="2.5">
      <manifest-digest sha256new="4NG3EEULVSDJNIXGTKT24QIPNYKVLU5R2GAZ7Z3R7JHL5D6LPIWQ"/>
      <archive extract="golly-2.5-win" href="http://downloads.sourceforge.net/golly/golly-2.5-win.zip" size="3847892" type="application/zip"/>
    </implementation>
    <implementation arch="Linux-i586" id="sha1new=5a17bf48c722f239e44c8f5c559412003026431e" main="golly" released="2013-06-15" stability="stable" version="2.5">
      <manifest-digest sha256new="GXV3RG6QSHHIMJERD4CSWSUUNJKZ3ZA5G7Q4UGLG76UYUAAZL76Q"/>
      <archive extract="golly-2.5-gtk" href="http://downloads.sourceforge.net/golly/golly-2.5-gtk.tar.gz" size="4041386"/>
    </implementation>
    <implementation arch="*-src" id="sha1new=6d03c3582164fd23803d93b949b11b8039a63e97" released="2013-06-15" stability="stable" version="2.5">
      <manifest-digest sha256new="6QPP2M4PDXT4CVFYHDM2YJJG4C5XCEZZNQWDCEXVMVN66X2PY4MQ"/>
      <archive extract="golly-2.5-src" href="http://downloads.sourceforge.net/golly/golly-2.5-src.tar.gz" size="3381010"/>
    </implementation>
    <implementation arch="Windows-*" id="sha1new=225b83fda9a2b44bdddfc6078ab832a43c41d23d" main="Golly.exe" released="2014-08-26" stability="stable" version="2.6">
      <manifest-digest sha256new="M6XLM2KTAPI3AWW2E56OG6J4BMIUILUVOETUUGYCMJDDDVLCSXGQ"/>
      <archive extract="golly-2.6-win" href="http://downloads.sourceforge.net/golly/golly-2.6-win.zip" size="3908481" type="application/zip"/>
    </implementation>
    <implementation arch="Linux-i586" id="sha1new=757dbc12cf4d871d73ebfa2255bb2199a2946c85" main="golly" released="2014-08-26" stability="stable" version="2.6">
      <manifest-digest sha256new="EGYGPZOUSG6GFPO52YHMVJ6NA4CVZ2433ZT37F6F46RO3FT6SZOA"/>
      <archive extract="golly-2.6-gtk" href="http://downloads.sourceforge.net/golly/golly-2.6-gtk.tar.gz" size="4104124"/>
    </implementation>
    <implementation arch="*-src" id="sha1new=3eab1ad00c846c2d93527708d7014f2819fde51b" released="2014-08-26" stability="stable" version="2.6">
      <manifest-digest sha256new="ONNG3TIDVJQBEWQIEF3DSHKEA7JHS4KLP67DUFAHHUGMBYNEDKVA"/>
      <archive extract="golly-2.6-src" href="http://downloads.sourceforge.net/golly/golly-2.6-src.tar.gz" size="3545388"/>
    </implementation>
  </group>
</interface>
